{
  "generated_at": "2026-06-06T15:10:10.054153+00:00",
  "anchor": "2026-04-01",
  "as_of": "2026-06-06",
  "bands": [
    {
      "label": "3D",
      "start": "2026-06-04",
      "end": "2026-06-06",
      "record": "6-3",
      "wins": 6,
      "losses": 3,
      "units_pl": 0.11,
      "roi_pct": 1.15,
      "n": 9,
      "vs_spx": 3.4,
      "vs_dji": 0.8,
      "vs_ndx": 5.41,
      "spx_return_pct": -2.25,
      "dji_return_pct": 0.35,
      "ndx_return_pct": -4.26
    },
    {
      "label": "7D",
      "start": "2026-05-31",
      "end": "2026-06-06",
      "record": "15-7",
      "wins": 15,
      "losses": 7,
      "units_pl": 1.68,
      "roi_pct": 7.38,
      "n": 22,
      "vs_spx": 9.97,
      "vs_dji": 7.7,
      "vs_ndx": 12.06,
      "spx_return_pct": -2.59,
      "dji_return_pct": -0.32,
      "ndx_return_pct": -4.68
    },
    {
      "label": "MTD",
      "start": "2026-06-01",
      "end": "2026-06-06",
      "record": "12-7",
      "wins": 12,
      "losses": 7,
      "units_pl": 0.0,
      "roi_pct": 0.02,
      "n": 19,
      "vs_spx": 2.61,
      "vs_dji": 0.34,
      "vs_ndx": 4.7,
      "spx_return_pct": -2.59,
      "dji_return_pct": -0.32,
      "ndx_return_pct": -4.68
    },
    {
      "label": "30D",
      "start": "2026-05-08",
      "end": "2026-06-06",
      "record": "68-56",
      "wins": 68,
      "losses": 56,
      "units_pl": -8.51,
      "roi_pct": -6.21,
      "n": 124,
      "vs_spx": -6.85,
      "vs_dji": -8.77,
      "vs_ndx": -5.84,
      "spx_return_pct": 0.64,
      "dji_return_pct": 2.56,
      "ndx_return_pct": -0.37
    },
    {
      "label": "ALL-TIME",
      "start": "2026-04-01",
      "end": "2026-06-06",
      "record": "207-172",
      "wins": 207,
      "losses": 172,
      "units_pl": -4.91,
      "roi_pct": -1.07,
      "n": 379,
      "vs_spx": -13.36,
      "vs_dji": -10.31,
      "vs_ndx": -18.78,
      "spx_return_pct": 12.29,
      "dji_return_pct": 9.24,
      "ndx_return_pct": 17.71
    }
  ],
  "indices": {
    "spx": {
      "date": "2026-06-05",
      "close": 7383.740234375
    },
    "dji": {
      "date": "2026-06-05",
      "close": 50866.78125
    },
    "ndx": {
      "date": "2026-06-05",
      "close": 25709.4296875
    }
  }
}
