{
  "generated_at": "2026-07-21T15:30:42.236590+00:00",
  "anchor": "2026-04-01",
  "as_of": "2026-07-21",
  "bands": [
    {
      "label": "3D",
      "start": "2026-07-19",
      "end": "2026-07-21",
      "record": "1-3",
      "wins": 1,
      "losses": 3,
      "units_pl": -3.09,
      "roi_pct": -77.27,
      "n": 4,
      "vs_spx": -77.9,
      "vs_dji": -77.36,
      "vs_ndx": -78.53,
      "spx_return_pct": 0.63,
      "dji_return_pct": 0.09,
      "ndx_return_pct": 1.26
    },
    {
      "label": "7D",
      "start": "2026-07-15",
      "end": "2026-07-21",
      "record": "3-10",
      "wins": 3,
      "losses": 10,
      "units_pl": -10.39,
      "roi_pct": -68.11,
      "n": 13,
      "vs_spx": -67.59,
      "vs_dji": -67.51,
      "vs_ndx": -67.1,
      "spx_return_pct": -0.52,
      "dji_return_pct": -0.6,
      "ndx_return_pct": -1.01
    },
    {
      "label": "21D",
      "start": "2026-07-01",
      "end": "2026-07-21",
      "record": "32-31",
      "wins": 32,
      "losses": 31,
      "units_pl": -4.29,
      "roi_pct": -6.53,
      "n": 63,
      "vs_spx": -6.6,
      "vs_dji": -6.29,
      "vs_ndx": -5.12,
      "spx_return_pct": 0.07,
      "dji_return_pct": -0.24,
      "ndx_return_pct": -1.41
    },
    {
      "label": "MTD",
      "start": "2026-07-01",
      "end": "2026-07-21",
      "record": "32-31",
      "wins": 32,
      "losses": 31,
      "units_pl": -4.29,
      "roi_pct": -6.53,
      "n": 63,
      "vs_spx": -6.6,
      "vs_dji": -6.29,
      "vs_ndx": -5.12,
      "spx_return_pct": 0.07,
      "dji_return_pct": -0.24,
      "ndx_return_pct": -1.41
    },
    {
      "label": "30D",
      "start": "2026-06-22",
      "end": "2026-07-21",
      "record": "47-45",
      "wins": 47,
      "losses": 45,
      "units_pl": -6.4,
      "roi_pct": -6.74,
      "n": 92,
      "vs_spx": -6.79,
      "vs_dji": -7.96,
      "vs_ndx": -4.19,
      "spx_return_pct": 0.05,
      "dji_return_pct": 1.22,
      "ndx_return_pct": -2.55
    },
    {
      "label": "ALL-TIME",
      "start": "2026-04-01",
      "end": "2026-07-21",
      "record": "287-251",
      "wins": 287,
      "losses": 251,
      "units_pl": -15.91,
      "roi_pct": -2.55,
      "n": 538,
      "vs_spx": -16.68,
      "vs_dji": -14.64,
      "vs_ndx": -20.87,
      "spx_return_pct": 14.13,
      "dji_return_pct": 12.09,
      "ndx_return_pct": 18.32
    }
  ],
  "indices": {
    "spx": {
      "date": "2026-07-21",
      "close": 7504.330078125
    },
    "dji": {
      "date": "2026-07-21",
      "close": 52193.62109375
    },
    "ndx": {
      "date": "2026-07-21",
      "close": 25842.8671875
    }
  }
}
